setup.py
hahatest/__init__.py
hahatest.egg-info/PKG-INFO
hahatest.egg-info/SOURCES.txt
hahatest.egg-info/dependency_links.txt
hahatest.egg-info/entry_points.txt
hahatest.egg-info/top_level.txt