Metadata-Version: 1.0
Name: hahatest
Version: 0.0.5
Summary: 测试测试
Home-page: https://abc.xyz
Author: heliang
Author-email: heliang.whut@gmail.com
License: UNKNOWN
Platform: UNKNOWN
